Metadata-Version: 2.1
Name: snugthon
Version: 0.1.0
Summary: Snug for python3.
Home-page: https://gitlab.com/snuglibs/snugthon
Author: aiocat
Author-email: 
License: MIT
Project-URL: Bug Tracker, https://gitlab.com/snuglibs/snugthon/-/issues
Keywords: snug,config
Platform: UNKNOWN
Classifier: Operating System :: OS Independent
Classifier: Development Status :: 4 - Beta
Classifier: Intended Audience :: Developers
Classifier: License :: OSI Approved :: MIT License
Classifier: Programming Language :: Python :: 3
Requires-Python: >=3.6.0
License-File: LICENSE
